<?xml version="1.0" encoding="UTF-8"?>
<level name="Level 1" number="1">
	<counter maxActions="1"/>
	<grid exactNumColumns="9" exactNumLines="7" maxGridSpacing="150"/>
	<dottedOutlines>
		<dottedOutline>
			<contour>
				<point column="4" line="5" />
				<point column="6" line="5" />
				<point column="6" line="4" />
				<point column="7" line="4" />
				<point column="7" line="3" />
				<point column="3" line="3" />
				<point column="3" line="4" />
				<point column="4" line="4" />
			</contour>
		</dottedOutline>
	</dottedOutlines>
	<shapes>
		<!-- <shape color="1,0,0">
			<contour>
				<point column="3" line="4"/>
				<point column="3" line="3"/>
				<point column="5" line="3"/>
				<point column="5" line="5"/>
				<point column="4" line="5"/>
				<point column="4" line="4"/>
			</contour>
		</shape> -->
		
		<shape tint="0">
			<contour>
				<point column="3" line="4"/>
				<point column="3" line="3"/>
				<point column="5" line="3"/>
				<point column="5" line="5"/>
				<point column="4" line="5"/>
				<point column="4" line="4"/>
			</contour>
		</shape>
		
<!--		<shape color="1,1,0">
			<contour>
				<point column="6" line="3"/>
				<point column="10" line="3"/>
				<point column="10" line="7"/>
				<point column="6" line="7"/>
			</contour>
		</shape>
		
		<shape color="0,1,0">
			<contour>
				<point column="4" line="1"/>
				<point column="6" line="1"/>
				<point column="6" line="2"/>
				<point column="4" line="2"/>
			</contour>
		</shape>
			
 		<shape color="0,1,0">
			<contour>
				<point column="4" line="5"/>
				<point column="2" line="5"/>
				<point column="2" line="2"/>
				<point column="6" line="2"/>
				<point column="6" line="5"/>
				<point column="4" line="5"/>
				<point column="5" line="4"/>
				<point column="4" line="3"/>
				<point column="3" line="4"/>
			</contour>
		</shape> -->
	</shapes>
	<constraints>
		<constraint tag="SYMMETRY_AXES_STRAIGHT"/>
		<constraint tag="SYMMETRY_AXES_DIAGONALS"/>
		<!-- 		
		<constraint tag="SYMMETRY_AXIS_HORIZONTAL"/>
		<constraint tag="SYMMETRY_AXIS_VERTICAL"/>
		<constraint tag="SYMMETRY_AXES_STRAIGHT"/>
		<constraint tag="SYMMETRY_AXIS_DIAGONAL_LEFT"/>
		<constraint tag="SYMMETRY_AXIS_DIAGONAL_RIGHT"/>
		<constraint tag="SYMMETRY_AXES_DIAGONALS"/>
		<constraint tag="SYMMETRY_AXES_ALL"/>
		<constraint tag="SYMMETRY_POINT"/> 
		-->
	</constraints>
</level>